Metadata-Version: 1.2
Name: craterstudiotask
Version: 0.0.1
Summary: Getting data of mesh objects from .ma example files
Home-page: UNKNOWN
Author: Uros Jevtic
Author-email: meksa96@gmail.com
License: MIT
Keywords: parser
Platform: UNKNOWN
Classifier: Development Status :: 5 - Production/Stable
Classifier: Intended Audience :: Education
Classifier: Operating System :: Microsoft :: Windows :: Windows 10
Classifier: License :: OSI Approved :: MIT License
Classifier: Programming Language :: Python
Requires-Python: >=2.7
